odoo/addons/delivery_carrier_pricelist/README.rst
odoo/addons/delivery_carrier_pricelist/__init__.py
odoo/addons/delivery_carrier_pricelist/__manifest__.py
odoo/addons/delivery_carrier_pricelist/i18n/delivery_carrier_pricelist.pot
odoo/addons/delivery_carrier_pricelist/i18n/es.po
odoo/addons/delivery_carrier_pricelist/i18n/it.po
odoo/addons/delivery_carrier_pricelist/models/__init__.py
odoo/addons/delivery_carrier_pricelist/models/delivery_carrier.py
odoo/addons/delivery_carrier_pricelist/models/stock_picking.py
odoo/addons/delivery_carrier_pricelist/readme/CONTRIBUTORS.md
odoo/addons/delivery_carrier_pricelist/readme/CREDITS.md
odoo/addons/delivery_carrier_pricelist/readme/DESCRIPTION.md
odoo/addons/delivery_carrier_pricelist/security/ir.model.access.csv
odoo/addons/delivery_carrier_pricelist/static/description/icon.png
odoo/addons/delivery_carrier_pricelist/static/description/index.html
odoo/addons/delivery_carrier_pricelist/tests/__init__.py
odoo/addons/delivery_carrier_pricelist/tests/test_delivery_pricelist.py
odoo/addons/delivery_carrier_pricelist/wizards/__init__.py
odoo/addons/delivery_carrier_pricelist/wizards/choose_delivery_carrier.py
odoo_addon_delivery_carrier_pricelist-18.0.1.0.1.dist-info/METADATA
odoo_addon_delivery_carrier_pricelist-18.0.1.0.1.dist-info/WHEEL
odoo_addon_delivery_carrier_pricelist-18.0.1.0.1.dist-info/top_level.txt
odoo_addon_delivery_carrier_pricelist-18.0.1.0.1.dist-info/RECORD
